sentry_protos/__init__.py
sentry_protos/py.typed
sentry_protos/conduit/__init__.py
sentry_protos/conduit/v1alpha/__init__.py
sentry_protos/conduit/v1alpha/publish_pb2.py
sentry_protos/conduit/v1alpha/publish_pb2.pyi
sentry_protos/conduit/v1alpha/publish_pb2_grpc.py
sentry_protos/conduit/v1alpha/publish_pb2_grpc.pyi
sentry_protos/kafka/__init__.py
sentry_protos/kafka/events/__init__.py
sentry_protos/kafka/events/v1/__init__.py
sentry_protos/kafka/events/v1/events_pb2.py
sentry_protos/kafka/events/v1/events_pb2.pyi
sentry_protos/kafka/events/v1/events_pb2_grpc.py
sentry_protos/kafka/events/v1/events_pb2_grpc.pyi
sentry_protos/options/__init__.py
sentry_protos/options/v1/__init__.py
sentry_protos/options/v1/options_pb2.py
sentry_protos/options/v1/options_pb2.pyi
sentry_protos/options/v1/options_pb2_grpc.py
sentry_protos/options/v1/options_pb2_grpc.pyi
sentry_protos/options/v1/topics_pb2.py
sentry_protos/options/v1/topics_pb2.pyi
sentry_protos/options/v1/topics_pb2_grpc.py
sentry_protos/options/v1/topics_pb2_grpc.pyi
sentry_protos/relay/__init__.py
sentry_protos/relay/v1/__init__.py
sentry_protos/relay/v1/event_pb2.py
sentry_protos/relay/v1/event_pb2.pyi
sentry_protos/relay/v1/event_pb2_grpc.py
sentry_protos/relay/v1/event_pb2_grpc.pyi
sentry_protos/seer/__init__.py
sentry_protos/seer/v1/__init__.py
sentry_protos/seer/v1/common_pb2.py
sentry_protos/seer/v1/common_pb2.pyi
sentry_protos/seer/v1/common_pb2_grpc.py
sentry_protos/seer/v1/common_pb2_grpc.pyi
sentry_protos/seer/v1/summarize_pb2.py
sentry_protos/seer/v1/summarize_pb2.pyi
sentry_protos/seer/v1/summarize_pb2_grpc.py
sentry_protos/seer/v1/summarize_pb2_grpc.pyi
sentry_protos/sentry/__init__.py
sentry_protos/sentry/v1/__init__.py
sentry_protos/sentry/v1/taskworker_pb2.py
sentry_protos/sentry/v1/taskworker_pb2.pyi
sentry_protos/sentry/v1/taskworker_pb2_grpc.py
sentry_protos/sentry/v1/taskworker_pb2_grpc.pyi
sentry_protos/snuba/__init__.py
sentry_protos/snuba/v1/__init__.py
sentry_protos-0.4.11.dist-info/licenses/LICENSE.md
sentry_protos-0.4.11.dist-info/METADATA
sentry_protos-0.4.11.dist-info/WHEEL
sentry_protos-0.4.11.dist-info/top_level.txt
sentry_protos-0.4.11.dist-info/RECORD
