Metadata-Version: 2.4
Name: sentry-protos
Version: 0.4.11
Summary: Generated python code for sentry-protos
License: # Functional Source License, Version 1.1, Apache 2.0 Future License
Project-URL: Homepage, https://sentry.io
Project-URL: Repository, https://github.com/getsentry/sentry-protos
Project-URL: Changelog, https://github.com/getsentry/sentry-protos/tree/main/CHANGELOG.md
Requires-Python: >3.10
License-File: LICENSE.md
Requires-Dist: protobuf<6,>=5.27.3
Requires-Dist: grpcio<2,>=1.59
Requires-Dist: grpc-stubs<2,>=1.53
Dynamic: license-file
